whitepossum-0.6.4.dist-info/METADATA
whitepossum-0.6.4.dist-info/WHEEL
whitepossum/__init__.py
whitepossum/_core.abi3.so
whitepossum/_core.pyi
whitepossum/differential/__init__.py
whitepossum/differential/discrete.py
whitepossum/distributions/__init__.py
whitepossum/distributions/cvdistributions.py
whitepossum/matrix/__init__.py
whitepossum/matrix/elementary.py
whitepossum/model/__init__.py
whitepossum/model/regression.py
whitepossum/py.typed
whitepossum-0.6.4.dist-info/RECORD
