Metadata-Version: 2.4
Name: whitepossum
Version: 0.6.4
Requires-Dist: matplotlib>=3.10.6
Requires-Dist: numpy>=2.3.3
Requires-Dist: polars>=1.34.0
Requires-Dist: scipy>=1.16.2
Requires-Dist: torch>=2.8.0
Requires-Dist: twine>=6.1.0
Summary: This package implements differential functions
Author-email: whitepossum <whitepossum@andrewnw.com>
Requires-Python: >=3.12
